lmdb.h
mdb.c
midl.c
midl.h
lmdb/__init__.py
lmdb/__main__.py
lmdb/_config.py
lmdb/cffi.py
lmdb/tool.py
lmdb-1.7.5.dist-info/licenses/LICENSE
py-lmdb/env-copy-txn.patch
py-lmdb/its-10346.patch
py-lmdb/preload.h
win32/inttypes.h
win32/unistd.h
win32-stdint/stdint.h
lmdb-1.7.5.dist-info/METADATA
lmdb-1.7.5.dist-info/WHEEL
lmdb-1.7.5.dist-info/top_level.txt
lmdb-1.7.5.dist-info/RECORD
