Metadata-Version: 2.4
Name: lmdb
Version: 1.7.5
Summary: Universal Python binding for the LMDB 'Lightning' Database
Home-page: http://github.com/jnwatson/py-lmdb/
Author: David Wilson
Maintainer: Nic Watson
License: OLDAP-2.8
Classifier: Programming Language :: Python
Classifier: Programming Language :: Python :: Implementation :: CPython
Classifier: Programming Language :: Python :: Implementation :: PyPy
Classifier: Programming Language :: Python :: 3
Classifier: Programming Language :: Python :: 3.5
Classifier: Programming Language :: Python :: 3.6
Classifier: Programming Language :: Python :: 3.7
Classifier: Programming Language :: Python :: 3.8
Classifier: Programming Language :: Python :: 3.9
Classifier: Programming Language :: Python :: 3.10
Classifier: Programming Language :: Python :: 3.11
Classifier: Programming Language :: Python :: 3.12
Classifier: Programming Language :: Python :: 3.13
Classifier: Programming Language :: Python :: 3.14
Classifier: Topic :: Database
Classifier: Topic :: Database :: Database Engines/Servers
License-File: LICENSE
Requires-Dist: cffi>=0.8
Dynamic: author
Dynamic: classifier
Dynamic: description
Dynamic: description-content-type
Dynamic: home-page
Dynamic: license
Dynamic: license-file
Dynamic: maintainer
Dynamic: requires-dist
Dynamic: summary
